[
  {
    "arch": "arm64",
    "filename": "rtorrent-linux-arm64.deb",
    "package": "Package: rtorrent\nVersion: 0.9.8-jc-r16\nArchitecture: arm64\nMaintainer: Jesse Chan <jc@linux.com>\nFilename: ./pool/main/jesec/rtorrent/v0.9.8-r16/rtorrent-linux-arm64.deb\nSize: 2037196\nMD5sum: bc562648f10696d697f02d977cb5329d\nSHA1: 51eec894b0e0b9c145e67be7de5ac43c319c80be\nSHA256: c536a55ea82462c2b6dee4b56e0975f9ff9d36cc73441208243cf6e78f591804\nSection: contrib/devel\nPriority: optional\nHomepage: https://github.com/jesec/rtorrent\nDescription: a stable and high-performance BitTorrent client\n\n",
    "published_at": "2022-04-17T02:43:24+00:00",
    "tag": "v0.9.8-r16"
  },
  {
    "arch": "amd64",
    "filename": "rtorrent-linux-amd64.deb",
    "package": "Package: rtorrent\nVersion: 0.9.8-jc-r16\nArchitecture: amd64\nMaintainer: Jesse Chan <jc@linux.com>\nFilename: ./pool/main/jesec/rtorrent/v0.9.8-r16/rtorrent-linux-amd64.deb\nSize: 2176364\nMD5sum: 851ac112124c60aca90738fa99643d77\nSHA1: 18cc42f57cee7a170e32451137e28c64aa4246f7\nSHA256: 880dafaa37e57d86e0898a1e03ca5050471a768c684cb2267708ef0487377e89\nSection: contrib/devel\nPriority: optional\nHomepage: https://github.com/jesec/rtorrent\nDescription: a stable and high-performance BitTorrent client\n\n",
    "published_at": "2022-04-17T02:43:24+00:00",
    "tag": "v0.9.8-r16"
  },
  {
    "arch": "arm64",
    "filename": "rtorrent-linux-arm64.deb",
    "package": "Package: rtorrent\nVersion: 0.9.8-jc-r15\nArchitecture: arm64\nMaintainer: Jesse Chan <jc@linux.com>\nFilename: ./pool/main/jesec/rtorrent/v0.9.8-r15/rtorrent-linux-arm64.deb\nSize: 1891808\nMD5sum: 38ed926b2060f30fa62c76c907c7ec6c\nSHA1: ff980f23e07f5e4472e0703d3367b4b121a7106a\nSHA256: 917798997d89f62f4009af49664660ec33ca9dfd35b064566d28725b5fe49bcf\nSection: contrib/devel\nPriority: optional\nHomepage: https://github.com/jesec/rtorrent\nDescription: a stable and high-performance BitTorrent client\n\n",
    "published_at": "2021-10-09T21:19:34+00:00",
    "tag": "v0.9.8-r15"
  },
  {
    "arch": "amd64",
    "filename": "rtorrent-linux-amd64.deb",
    "package": "Package: rtorrent\nVersion: 0.9.8-jc-r15\nArchitecture: amd64\nMaintainer: Jesse Chan <jc@linux.com>\nFilename: ./pool/main/jesec/rtorrent/v0.9.8-r15/rtorrent-linux-amd64.deb\nSize: 2184722\nMD5sum: 32a56e85ec554c954ddbe0bed453f5bd\nSHA1: c151a07a8fa4d650155f466bec544fc1c9704d02\nSHA256: 106e3969dd8583994a899ea104b0828bb887caab0e6cda872c624d228a62aa7a\nSection: contrib/devel\nPriority: optional\nHomepage: https://github.com/jesec/rtorrent\nDescription: a stable and high-performance BitTorrent client\n\n",
    "published_at": "2021-10-09T21:19:34+00:00",
    "tag": "v0.9.8-r15"
  },
  {
    "arch": "arm64",
    "filename": "rtorrent-linux-arm64.deb",
    "package": "Package: rtorrent\nVersion: 0.9.8-jc-r14\nArchitecture: arm64\nMaintainer: Jesse Chan <jc@linux.com>\nFilename: ./pool/main/jesec/rtorrent/v0.9.8-r14/rtorrent-linux-arm64.deb\nSize: 1850438\nMD5sum: 817494f23eb48eda90fee772ca9661c7\nSHA1: 29a4045d14d418729111f0fe6a9ef3b1dbf1605a\nSHA256: f49bd933f630879fdea3a841e81e457b1e40ee789096607e544d9c2941c44d0d\nSection: contrib/devel\nPriority: optional\nHomepage: https://github.com/jesec/rtorrent\nDescription: a stable and high-performance BitTorrent client\n\n",
    "published_at": "2021-05-28T11:24:38+00:00",
    "tag": "v0.9.8-r14"
  },
  {
    "arch": "amd64",
    "filename": "rtorrent-linux-amd64.deb",
    "package": "Package: rtorrent\nVersion: 0.9.8-jc-r14\nArchitecture: amd64\nMaintainer: Jesse Chan <jc@linux.com>\nFilename: ./pool/main/jesec/rtorrent/v0.9.8-r14/rtorrent-linux-amd64.deb\nSize: 2143140\nMD5sum: 959aaa85e9ac55a10ce0498308cb248e\nSHA1: 0585153a0c4a63761999f9fe12ffd29b6180a46e\nSHA256: 2a1f0e4c61c1474e8b56cbe673f47a41642fc6a51eab9177145ace1c327af768\nSection: contrib/devel\nPriority: optional\nHomepage: https://github.com/jesec/rtorrent\nDescription: a stable and high-performance BitTorrent client\n\n",
    "published_at": "2021-05-28T11:24:38+00:00",
    "tag": "v0.9.8-r14"
  }
]